[{"formattedAddress":"201 W Washington Blvd, Los Angeles, CA 90015, USA","latitude":34.03240580000001,"longitude":-118.2669604,"extra":{"googlePlaceId":"ChIJ46hEIcXHwoARfTrRp15Lt2o","confidence":1,"premise":null,"subpremise":null,"neighborhood":"South Los Angeles","establishment":null},"administrativeLevels":{"level2long":"Los Angeles County","level2short":"Los Angeles County","level1long":"California","level1short":"CA"},"streetNumber":"201","streetName":"West Washington Boulevard","city":"Los Angeles","country":"United States","countryCode":"US","zipcode":"90015","provider":"google"},{"formattedAddress":"4011 S Central Ave, Los Angeles, CA 90011, USA","latitude":34.0105442,"longitude":-118.2569161,"extra":{"googlePlaceId":"ChIJ50OAoWPIwoAR5yVBtaMZmiw","confidence":1,"premise":null,"subpremise":null,"neighborhood":"South Los Angeles","establishment":null},"administrativeLevels":{"level2long":"Los Angeles County","level2short":"Los Angeles County","level1long":"California","level1short":"CA"},"streetNumber":"4011","streetName":"South Central Avenue","city":"Los Angeles","country":"United States","countryCode":"US","zipcode":"90011","provider":"google"},{"formattedAddress":"2810 S Figueroa St, Los Angeles, CA 90007, USA","latitude":34.0260793,"longitude":-118.2769181,"extra":{"googlePlaceId":"ChIJ-20xd-fHwoARBKvUWGCAmNQ","confidence":1,"premise":null,"subpremise":null,"neighborhood":"South Los Angeles","establishment":null},"administrativeLevels":{"level2long":"Los Angeles County","level2short":"Los Angeles County","level1long":"California","level1short":"CA"},"streetNumber":"2810","streetName":"South Figueroa Street","city":"Los Angeles","country":"United States","countryCode":"US","zipcode":"90007","provider":"google"},{"formattedAddress":"1311 W Washington Blvd, Los Angeles, CA 90007, USA","latitude":34.0403804,"longitude":-118.2844088,"extra":{"googlePlaceId":"ChIJc2HZrZPHwoAR9KDqU9ur_wk","confidence":1,"premise":null,"subpremise":null,"neighborhood":"Mid City","establishment":null},"administrativeLevels":{"level2long":"Los Angeles County","level2short":"Los Angeles County","level1long":"California","level1short":"CA"},"streetNumber":"1311","streetName":"West Washington Boulevard","city":"Los Angeles","country":"United States","countryCode":"US","zipcode":"90007","provider":"google"},{"formattedAddress":"1625 Wilshire Blvd, Los Angeles, CA 90017, USA","latitude":34.0559576,"longitude":-118.2708202,"extra":{"googlePlaceId":"ChIJ18AW_aPHwoARXRm-cgcRcDs","confidence":1,"premise":null,"subpremise":null,"neighborhood":"Westlake","establishment":null},"administrativeLevels":{"level2long":"Los Angeles County","level2short":"Los Angeles County","level1long":"California","level1short":"CA"},"streetNumber":"1625","streetName":"Wilshire Boulevard","city":"Los Angeles","country":"United States","countryCode":"US","zipcode":"90017","provider":"google"},{"formattedAddress":"2838 Crenshaw Blvd, Los Angeles, CA 90016, USA","latitude":34.0302901,"longitude":-118.3347381,"extra":{"googlePlaceId":"ChIJg3HiVk-4woAR4AC8YZlhaQU","confidence":1,"premise":null,"subpremise":null,"neighborhood":"South Los Angeles","establishment":null},"administrativeLevels":{"level2long":"Los Angeles County","level2short":"Los Angeles County","level1long":"California","level1short":"CA"},"streetNumber":"2838","streetName":"Crenshaw Boulevard","city":"Los Angeles","country":"United States","countryCode":"US","zipcode":"90016","provider":"google"},{"formattedAddress":"3501 S La Cienega Blvd, Los Angeles, CA 90016, USA","latitude":34.0239993,"longitude":-118.3727473,"extra":{"googlePlaceId":"ChIJz7qbC5e5woARvFptlca1Hf4","confidence":1,"premise":null,"subpremise":null,"neighborhood":"South Los Angeles","establishment":null},"administrativeLevels":{"level2long":"Los Angeles County","level2short":"Los Angeles County","level1long":"California","level1short":"CA"},"streetNumber":"3501","streetName":"South La Cienega Boulevard","city":"Los Angeles","country":"United States","countryCode":"US","zipcode":"90016","provider":"google"},{"formattedAddress":"1231 South La Brea Ave, Los Angeles, CA 90019, USA","latitude":34.0525197,"longitude":-118.3443,"extra":{"googlePlaceId":"ChIJe4cHOv24woARH9eQifdcz28","confidence":1,"premise":null,"subpremise":null,"neighborhood":"Mid City","establishment":null},"administrativeLevels":{"level2long":"Los Angeles County","level2short":"Los Angeles County","level1long":"California","level1short":"CA"},"streetNumber":"1231","streetName":"South La Brea Avenue","city":"Los Angeles","country":"United States","countryCode":"US","zipcode":"90019","provider":"google"},{"formattedAddress":"6345 Wilshire Blvd, Los Angeles, CA 90048, USA","latitude":34.0639341,"longitude":-118.3667645,"extra":{"googlePlaceId":"ChIJ7-113zi5woAR74Rm5kP-yMs","confidence":1,"premise":null,"subpremise":null,"neighborhood":"Central LA","establishment":null},"administrativeLevels":{"level2long":"Los Angeles County","level2short":"Los Angeles County","level1long":"California","level1short":"CA"},"streetNumber":"6345","streetName":"Wilshire Boulevard","city":"Los Angeles","country":"United States","countryCode":"US","zipcode":"90048","provider":"google"},{"formattedAddress":"344 Bathurst St, Toronto, ON M6J 1T9, Canada","latitude":43.652085,"longitude":-79.4062357,"extra":{"googlePlaceId":"ChIJ0xHAj-g0K4gRjdz5l_LVZms","confidence":1,"premise":null,"subpremise":null,"neighborhood":"Old Toronto","establishment":null},"administrativeLevels":{"level2long":"Toronto Division","level2short":"Toronto Division","level1long":"Ontario","level1short":"ON"},"streetNumber":"344","streetName":"Bathurst Street","city":"Toronto","country":"Canada","countryCode":"CA","zipcode":"M6J 1T9","provider":"google"},{"formattedAddress":"710 King St W, Toronto, ON M5V 2Y6, Canada","latitude":43.6440653,"longitude":-79.40336080000002,"extra":{"googlePlaceId":"ChIJ1_Jwh-A0K4gRVRCHiXafl1k","confidence":1,"premise":null,"subpremise":null,"neighborhood":"Old Toronto","establishment":null},"administrativeLevels":{"level2long":"Toronto Division","level2short":"Toronto Division","level1long":"Ontario","level1short":"ON"},"streetNumber":"710","streetName":"King Street West","city":"Toronto","country":"Canada","countryCode":"CA","zipcode":"M5V 2Y6","provider":"google"},{"formattedAddress":"160 Spadina Ave, Toronto, ON, Canada","latitude":43.648782,"longitude":-79.39675079999999,"extra":{"googlePlaceId":"ChIJq8cdZds0K4gRoHKwJkNcaNE","confidence":1,"premise":null,"subpremise":null,"neighborhood":"Old Toronto","establishment":null},"administrativeLevels":{"level2long":"Toronto Division","level2short":"Toronto Division","level1long":"Ontario","level1short":"ON"},"streetNumber":"160","streetName":"Spadina Avenue","city":"Toronto","country":"Canada","countryCode":"CA","provider":"google"},{"formattedAddress":"109 McCaul St, Toronto, ON M5T 2W7, Canada","latitude":43.6538638,"longitude":-79.39108329999999,"extra":{"googlePlaceId":"ChIJuZ9tXM80K4gRVMtYXL7e3Io","confidence":1,"premise":null,"subpremise":null,"neighborhood":"Old Toronto","establishment":null},"administrativeLevels":{"level2long":"Toronto Division","level2short":"Toronto Division","level1long":"Ontario","level1short":"ON"},"streetNumber":"109","streetName":"McCaul Street","city":"Toronto","country":"Canada","countryCode":"CA","zipcode":"M5T 2W7","provider":"google"},{"formattedAddress":"65 Front St W, Toronto, ON M5J 1E6, Canada","latitude":43.64531969999999,"longitude":-79.3804062,"extra":{"googlePlaceId":"ChIJKQDzOA41K4gRajQDdyzD990","confidence":1,"premise":null,"subpremise":null,"neighborhood":"Old Toronto","establishment":null},"administrativeLevels":{"level2long":"Toronto Division","level2short":"Toronto Division","level1long":"Ontario","level1short":"ON"},"streetNumber":"65","streetName":"Front Street West","city":"Toronto","country":"Canada","countryCode":"CA","zipcode":"M5J 1E6","provider":"google"},{"formattedAddress":"181 Bay St, Toronto, ON M5J 2V1, Canada","latitude":43.64726160000001,"longitude":-79.3785998,"extra":{"googlePlaceId":"ChIJ65biAi3L1IkR39X8KYF-sRo","confidence":1,"premise":null,"subpremise":null,"neighborhood":"Old Toronto","establishment":null},"administrativeLevels":{"level2long":"Toronto Division","level2short":"Toronto Division","level1long":"Ontario","level1short":"ON"},"streetNumber":"181","streetName":"Bay Street","city":"Toronto","country":"Canada","countryCode":"CA","zipcode":"M5J 2V1","provider":"google"},{"formattedAddress":"123 Yonge St, Toronto, ON M5C 1W4, Canada","latitude":43.6509255,"longitude":-79.37825529999999,"extra":{"googlePlaceId":"ChIJd5Zc4zLL1IkRmG90lQIu_X4","confidence":1,"premise":null,"subpremise":null,"neighborhood":"Old Toronto","establishment":null},"administrativeLevels":{"level2long":"Toronto Division","level2short":"Toronto Division","level1long":"Ontario","level1short":"ON"},"streetNumber":"123","streetName":"Yonge Street","city":"Toronto","country":"Canada","countryCode":"CA","zipcode":"M5C 1W4","provider":"google"},{"formattedAddress":"121 Front St E, Toronto, ON M5A 1E1, Canada","latitude":43.6494917,"longitude":-79.3704556,"extra":{"googlePlaceId":"ChIJaTOEaTDL1IkRBSfkgbg2uzs","confidence":1,"premise":null,"subpremise":null,"neighborhood":"Old Toronto","establishment":null},"administrativeLevels":{"level2long":"Toronto Division","level2short":"Toronto Division","level1long":"Ontario","level1short":"ON"},"streetNumber":"121","streetName":"Front Street East","city":"Toronto","country":"Canada","countryCode":"CA","zipcode":"M5A 1E1","provider":"google"},{"formattedAddress":"127 Church St, Toronto, ON M5C 1S1, Canada","latitude":43.6530798,"longitude":-79.3755279,"extra":{"googlePlaceId":"ChIJI2Ny9zPL1IkR_bNEsiOVsgw","confidence":1,"premise":null,"subpremise":null,"neighborhood":"Old Toronto","establishment":null},"administrativeLevels":{"level2long":"Toronto Division","level2short":"Toronto Division","level1long":"Ontario","level1short":"ON"},"streetNumber":"127","streetName":"Church Street","city":"Toronto","country":"Canada","countryCode":"CA","zipcode":"M5C 1S1","provider":"google"},{"formattedAddress":"356 Yonge St, Toronto, ON M5B 1S5, Canada","latitude":43.6581668,"longitude":-79.3821482,"extra":{"googlePlaceId":"ChIJBbmcmco0K4gRI8UU7PmEGJo","confidence":1,"premise":null,"subpremise":null,"neighborhood":"Old Toronto","establishment":null},"administrativeLevels":{"level2long":"Toronto Division","level2short":"Toronto Division","level1long":"Ontario","level1short":"ON"},"streetNumber":"356","streetName":"Yonge Street","city":"Toronto","country":"Canada","countryCode":"CA","zipcode":"M5B 1S5","provider":"google"},{"formattedAddress":"11 St Clair Ave E, Toronto, ON M4T 1L8, Canada","latitude":43.6881213,"longitude":-79.3931664,"extra":{"googlePlaceId":"ChIJrWYyNUUzK4gRjj8V10yCb_8","confidence":1,"premise":null,"subpremise":null,"neighborhood":"Old Toronto","establishment":null},"administrativeLevels":{"level2long":"Toronto Division","level2short":"Toronto Division","level1long":"Ontario","level1short":"ON"},"streetNumber":"11","streetName":"Saint Clair Avenue East","city":"Toronto","country":"Canada","countryCode":"CA","zipcode":"M4T 1L8","provider":"google"},{"formattedAddress":"710 St Clair Ave W, Toronto, ON M6C 1B2, Canada","latitude":43.6817695,"longitude":-79.4269164,"extra":{"googlePlaceId":"ChIJ8_CKin80K4gREL8tjrR-QAM","confidence":1,"premise":null,"subpremise":null,"neighborhood":"York","establishment":null},"administrativeLevels":{"level2long":"Toronto Division","level2short":"Toronto Division","level1long":"Ontario","level1short":"ON"},"streetNumber":"710","streetName":"Saint Clair Avenue West","city":"Toronto","country":"Canada","countryCode":"CA","zipcode":"M6C 1B2","provider":"google"},{"formattedAddress":"1168 St Clair Ave W, Toronto, ON M6E 1B4, Canada","latitude":43.678138,"longitude":-79.4434242,"extra":{"googlePlaceId":"ChIJu1BL8nM0K4gRNXE9BabRos8","confidence":1,"premise":null,"subpremise":null,"neighborhood":"Old Toronto","establishment":null},"administrativeLevels":{"level2long":"Toronto Division","level2short":"Toronto Division","level1long":"Ontario","level1short":"ON"},"streetNumber":"1168","streetName":"Saint Clair Avenue West","city":"Toronto","country":"Canada","countryCode":"CA","zipcode":"M6E 1B4","provider":"google"},{"formattedAddress":"Loftus St & Alfred St, Sydney NSW 2000, Australia","latitude":-33.8615143,"longitude":151.2105422,"extra":{"googlePlaceId":"EjFMb2Z0dXMgU3QgJiBBbGZyZWQgU3QsIFN5ZG5leSBOU1cgMjAwMCwgQXVzdHJhbGlhImYiZAoUChIJ9eya1GmuEmsRQGV-Sh8jHB8SFAoSCfXsmtRprhJrEUBlfkofIxwfGhQKEgnjqk_haa4SaxFnEO7s-tzC6RoUChIJXzFlf0KuEmsREzfA-NorPNciCg2ZJNHrFc7lIFo","confidence":0.7,"premise":null,"subpremise":null,"neighborhood":"Sydney","establishment":null},"administrativeLevels":{"level2long":"Council of the City of Sydney","level2short":"Sydney","level1long":"New South Wales","level1short":"NSW"},"city":"Sydney","country":"Australia","countryCode":"AU","zipcode":"2000","provider":"google"},{"formattedAddress":"Wynyard St &, Carrington St, Sydney NSW 2000, Australia","latitude":-33.865731,"longitude":151.2061545,"extra":{"googlePlaceId":"ChIJ0xyH_kCuEmsR-yW2usxv5qc","confidence":0.7,"premise":null,"subpremise":null,"neighborhood":"Sydney","establishment":null},"administrativeLevels":{"level2long":"Council of the City of Sydney","level2short":"Sydney","level1long":"New South Wales","level1short":"NSW"},"streetName":"Carrington Street","city":"Sydney","country":"Australia","countryCode":"AU","zipcode":"2000","provider":"google"},{"formattedAddress":"375/377 George St, Sydney NSW 2000, Australia","latitude":-33.8691836,"longitude":151.2068314,"extra":{"googlePlaceId":"ChIJ3RrGcz-uEmsR9tWE69WxntE","confidence":1,"premise":null,"subpremise":"375","neighborhood":"Sydney","establishment":null},"administrativeLevels":{"level2long":"Council of the City of Sydney","level2short":"Sydney","level1long":"New South Wales","level1short":"NSW"},"streetNumber":"377","streetName":"George Street","city":"Sydney","country":"Australia","countryCode":"AU","zipcode":"2000","provider":"google"},{"formattedAddress":"Market St, Sydney NSW 2000, Australia","latitude":-33.8701004,"longitude":151.2088972,"extra":{"googlePlaceId":"ChIJwWBUqD-uEmsRl9SNDJ2L86M","confidence":0.7,"premise":null,"subpremise":null,"neighborhood":"Sydney","establishment":null},"administrativeLevels":{"level2long":"Council of the City of Sydney","level2short":"Sydney","level1long":"New South Wales","level1short":"NSW"},"streetName":"Market Street","city":"Sydney","country":"Australia","countryCode":"AU","zipcode":"2000","provider":"google"},{"formattedAddress":"2-10 Darling Dr, Sydney NSW 2000, Australia","latitude":-33.8718551,"longitude":151.1988638,"extra":{"googlePlaceId":"ChIJx5K_CDquEmsRImanF5HhsqE","confidence":1,"premise":null,"subpremise":null,"neighborhood":"Sydney","establishment":null},"administrativeLevels":{"level2long":"Council of the City of Sydney","level2short":"Sydney","level1long":"New South Wales","level1short":"NSW"},"streetNumber":"2-10","streetName":"Darling Drive","city":"Sydney","country":"Australia","countryCode":"AU","zipcode":"2000","provider":"google"},{"formattedAddress":"1B Harbour St, Haymarket NSW 2000, Australia","latitude":-33.8775967,"longitude":151.2024455,"extra":{"googlePlaceId":"ChIJ8dUpzCSuEmsR-RfF9xMuWi0","confidence":1,"premise":null,"subpremise":null,"neighborhood":"Haymarket","establishment":null},"administrativeLevels":{"level2long":"Council of the City of Sydney","level2short":"Sydney","level1long":"New South Wales","level1short":"NSW"},"streetNumber":"1B","streetName":"Harbour Street","city":"Haymarket","country":"Australia","countryCode":"AU","zipcode":"2000","provider":"google"},{"formattedAddress":"600 George St, Sydney NSW 2000, Australia","latitude":-33.8754181,"longitude":151.2069202,"extra":{"googlePlaceId":"ChIJkzR8UTyuEmsRfEEpyLSN0C0","confidence":1,"premise":null,"subpremise":null,"neighborhood":"Sydney","establishment":null},"administrativeLevels":{"level2long":"Council of the City of Sydney","level2short":"Sydney","level1long":"New South Wales","level1short":"NSW"},"streetNumber":"600","streetName":"George Street","city":"Sydney","country":"Australia","countryCode":"AU","zipcode":"2000","provider":"google"},{"formattedAddress":"45-47 Darlinghurst Rd, Potts Point NSW 2011, Australia","latitude":-33.8735315,"longitude":151.2234723,"extra":{"googlePlaceId":"ChIJ-YynPw2uEmsRZ3Ew1K8Zkkk","confidence":1,"premise":null,"subpremise":null,"neighborhood":"Potts Point","establishment":null},"administrativeLevels":{"level2long":"Council of the City of Sydney","level2short":"Sydney","level1long":"New South Wales","level1short":"NSW"},"streetNumber":"45-47","streetName":"Darlinghurst Road","city":"Potts Point","country":"Australia","countryCode":"AU","zipcode":"2011","provider":"google"},{"formattedAddress":"Railway Square, 863 George St, Ultimo NSW 2007, Australia","latitude":-33.883753,"longitude":151.2024633,"extra":{"googlePlaceId":"ChIJW3I0jSauEmsReSCbXHl2jG0","confidence":1,"premise":null,"subpremise":null,"neighborhood":"Ultimo","establishment":null},"administrativeLevels":{"level2long":"Council of the City of Sydney","level2short":"Sydney","level1long":"New South Wales","level1short":"NSW"},"streetNumber":"863","streetName":"George Street","city":"Ultimo","country":"Australia","countryCode":"AU","zipcode":"2007","provider":"google"},{"formattedAddress":"11 Sulkhan Nasidze St, T'bilisi, Georgia","latitude":41.7158936,"longitude":44.77377740000001,"extra":{"googlePlaceId":"ChIJr8sLXSlzREARsTd9EVA-5xc","confidence":1,"premise":null,"subpremise":null,"neighborhood":"Vake-Saburtalo","establishment":null},"administrativeLevels":{"level1long":"Tbilisi","level1short":"Tbilisi"},"streetNumber":"11","streetName":"Sulkhan Nasidze Street","city":"T'bilisi","country":"Georgia","countryCode":"GE","provider":"google"},{"formattedAddress":"12 Viktor Dolidze St, T'bilisi, Georgia","latitude":41.7171435,"longitude":44.7753087,"extra":{"googlePlaceId":"ChIJi1gnmilzREARvVIRfSdELxM","confidence":1,"premise":null,"subpremise":null,"neighborhood":"Vake-Saburtalo","establishment":null},"administrativeLevels":{"level1long":"Tbilisi","level1short":"Tbilisi"},"streetNumber":"12","streetName":"Viktor Dolidze Street","city":"T'bilisi","country":"Georgia","countryCode":"GE","provider":"google"},{"formattedAddress":"29 Viktor Dolidze St, T'bilisi, Georgia","latitude":41.7171028,"longitude":44.7711537,"extra":{"googlePlaceId":"ChIJT-Ar3ChzREARujQ6aNLUBjQ","confidence":1,"premise":null,"subpremise":null,"neighborhood":"Vake-Saburtalo","establishment":null},"administrativeLevels":{"level1long":"Tbilisi","level1short":"Tbilisi"},"streetNumber":"29","streetName":"Viktor Dolidze Street","city":"T'bilisi","country":"Georgia","countryCode":"GE","provider":"google"},{"formattedAddress":"Merab Kostava St, T'bilisi, Georgia","latitude":41.7188857,"longitude":44.7784007,"extra":{"googlePlaceId":"ChIJn9WsFdZyREARAzxp3B4fKwo","confidence":0.7,"premise":null,"subpremise":null,"neighborhood":"Vake-Saburtalo","establishment":null},"administrativeLevels":{"level1long":"Tbilisi","level1short":"Tbilisi"},"streetName":"Merab Kostava Street","city":"T'bilisi","country":"Georgia","countryCode":"GE","provider":"google"},{"formattedAddress":"2 Viktor Dolidze St, T'bilisi, Georgia","latitude":41.7163404,"longitude":44.7683506,"extra":{"googlePlaceId":"ChIJpY9VOS9zREARr5wbGYvqswQ","confidence":1,"premise":null,"subpremise":null,"neighborhood":"Vake-Saburtalo","establishment":null},"administrativeLevels":{"level1long":"Tbilisi","level1short":"Tbilisi"},"streetNumber":"2","streetName":"Viktor Dolidze Street","city":"T'bilisi","country":"Georgia","countryCode":"GE","provider":"google"},{"formattedAddress":"150 Davit Aghmashenebeli Ave, T'bilisi, Georgia","latitude":41.7176363,"longitude":44.7911188,"extra":{"googlePlaceId":"ChIJNZV9uywNREAR9tNnE2a_fAM","confidence":1,"premise":null,"subpremise":null,"neighborhood":"Dzveli Tbilisi","establishment":null},"administrativeLevels":{"level1long":"Tbilisi","level1short":"Tbilisi"},"streetNumber":"150","streetName":"Davit Aghmashenebeli Avenue","city":"T'bilisi","country":"Georgia","countryCode":"GE","provider":"google"},{"formattedAddress":"Ia Kargareteli Street, T'bilisi, Georgia","latitude":41.7156713,"longitude":44.7945447,"extra":{"googlePlaceId":"ChIJN1SHDywNREARY-jfliKC_fM","confidence":0.7,"premise":null,"subpremise":null,"neighborhood":"Dzveli Tbilisi","establishment":null},"administrativeLevels":{"level1long":"Tbilisi","level1short":"Tbilisi"},"streetName":"Ia Kargareteli Street","city":"T'bilisi","country":"Georgia","countryCode":"GE","provider":"google"}]